[
  {
  "date": "2026-05-07",
  "title": "介護情報基盤 導入支援事業者に認定",
  "summary": "株式会社Airuは、介護情報基盤の導入支援事業者として、介護事業所を対象に導入支援を開始しました。"
  }
  {
  "date": "2026-05-01",
  "title": "日本HP販売店として法人PC支援を開始",
  "summary": "法人・行政向けPC導入支援サービスを開始しました。"
  }
  {
   "date": "2025-12-16",
   "title": "「ゼロから学ぶSNS活用術」開催のお知らせ",
   "summary": "SNS初心者向けセミナー「ゼロから学ぶSNS活用術」を2026年1月より開催します。",
   "content": "SNSって気になるけど、何から始めればいいかわからない。そんな方に向けた実践型セミナーです。",
   "image": "/images/seminar-sns-2026.png",
   "pdf": "/files/seminar-sns-2026.pdf"
  },
  {
    "date": "2025-09-16",
    "title": "株式会社Airu 公式サイトを公開しました",
    "body": "株式会社Airuの公式Webサイトを公開しました。"
  },
  {
    "date": "2025-09-16",
    "title": "事業内容ページを更新しました",
    "body": "提供サービスの内容を分かりやすく整理しました。"
  },
  {
    "date": "2025-09-16",
    "title": "ホームページ制作実績を追加しました",
    "body": "制作実績ページに新しい事例を追加しました。"
  }
]
